{
    "machine": "alambic_manaic",
    "registryName": "alambic_matrix_pigmentary",
    "recipeTime": 1200,
    "requirements": [
        {
            "type": "modularmachinery:energy",
            "io-type": "input",
            "energyPerTick": 2000
        },
        {
            "type": "modularmachinery:fluid",
            "io-type": "input",
            "fluid": "extract_sweet_red",
            "amount": 100
        },
        {
            "type": "modularmachinery:fluid",
            "io-type": "input",
            "fluid": "extract_sweet_orange",
            "amount": 100
        },
        {
            "type": "modularmachinery:fluid",
            "io-type": "input",
            "fluid": "extract_sweet_yellow",
            "amount": 100
        },
        {
            "type": "modularmachinery:fluid",
            "io-type": "input",
            "fluid": "extract_sweet_pink",
            "amount": 100
        },
        {
            "type": "modularmachinery:fluid",
            "io-type": "input",
            "fluid": "extract_sweet_lime",
            "amount": 100
        },
        {
            "type": "modularmachinery:fluid",
            "io-type": "input",
            "fluid": "extract_sweet_cyan",
            "amount": 100
        },
        {
            "type": "modularmachinery:fluid",
            "io-type": "input",
            "fluid": "extract_sweet_lightblue",
            "amount": 100
        },
        {
            "type": "modularmachinery:fluid",
            "io-type": "input",
            "fluid": "extract_sweet_magenta",
            "amount": 100
        },
        {
            "type": "modularmachinery:fluid",
            "io-type": "input",
            "fluid": "extract_dark_black",
            "amount": 100
        },
        {
            "type": "modularmachinery:fluid",
            "io-type": "input",
            "fluid": "extract_dark_purple",
            "amount": 100
        },
        {
            "type": "modularmachinery:fluid",
            "io-type": "input",
            "fluid": "extract_dark_brown",
            "amount": 100
        },
        {
            "type": "modularmachinery:item",
            "io-type": "input",
            "item": "botania:manaresource:5",
            "amount": 4
        },
        {
            "type": "modularmachinery:item",
            "io-type": "output",
            "item": "contenttweaker:matrix_pigmentary",
            "amount": 1
        },
        {
            "type": "modularmachinery:item",
            "io-type": "output",
            "item": "contenttweaker:mana_bound_capsule",
            "amount": 4
        }
    ]
}